{"hash":"133727dfa1d200b3fa68e92526218bf71d88953a","data":{"post":{"title":"Laravel Intelephense Errors","youtube":"","date":"January 19, 2022","content":"<h2 id=\"solution-for-method-error\"><a href=\"#solution-for-method-error\" aria-hidden=\"true\"><span class=\"icon icon-link\"></span></a>Solution for method error</h2>\n<p><a href=\"https://github.com/bmewburn/vscode-intelephense/issues/1116\" target=\"_blank\" rel=\"nofollow noopener noreferrer\">Method error solution</a></p>\n<p><code>(intelephense.diagnostics.undefinedTypes) - open settings in vs code and....</code></p>\n","fileInfo":{"extension":".md","directory":"blog","path":"blog/2022-01-19-laravel-intelephense-problems.md","name":"2022-01-19-laravel-intelephense-problems"},"tags":[{"title":"php","path":"/tag/php/"}]}},"context":{}}